[
  {
    "id": "54e1c764-8c6c-40ea-a7ba-bec0602ac8dd",
    "merchant_name": "Temujin's",
    "delivery_address": {
      "address_details": "muis 4iin hoino, shihihutagiin urd 45 bair 12 toot kod: 3421#",
      "address_notes": "null"
    },
    "pickup_address_full": "Код байхгүй. Нохойтой учир болгоомжил",
    "delivery_address_full": "test",
    "customer_name": "temujin",
    "customer_phone_extra": null,
    "customer_phone": "99230125",
    "total_amount": 4100000,
    "delivery_count": 1,
    "delivery_driver_name": null,
    "tracking_number": "TSH-3IAYH9NJMA15",
    "delivery_status": "created",
    "payment_status": "pending",
    "created_at": "2025-06-05T07:13:58.896Z",
    "updated_at": null,
    "is_canceled": false,
    "canceled_reason": null
  },
  {
    "id": "85d466da-5880-4bea-aa0d-c3cb74cce3e5",
    "merchant_name": "Munkh-Orgil's Online Store",
    "delivery_address": {
      "address_details": "muis 4iin hoino, shihihutagiin urd 45 bair 12 toot kod: 3421#",
      "address_notes": null
    },
    "pickup_address_full": "Улаанбаатар, Сүхбаатар, 1-р хороо",
    "delivery_address_full": "muis 4iin hoino, shihihutagiin urd 45 bair 12 toot kod: 3421#",
    "customer_name": "Тэмүжин",
    "customer_phone_extra": null,
    "customer_phone": "99230125",
    "total_amount": 4000000,
    "delivery_count": 1,
    "delivery_driver_name": null,
    "tracking_number": "MOS-17QSCB4RIBSQ",
    "delivery_status": "verified",
    "payment_status": "pending",
    "created_at": "2025-06-02T07:35:19.556Z",
    "updated_at": null,
    "is_canceled": false,
    "canceled_reason": null
  },
  {
    "id": "8cac4166-2cef-4dff-be0c-4e9cb2ac93dc",
    "merchant_name": "Temujin's shop",
    "delivery_address": null,
    "pickup_address_full": "Орцны код: 3463#",
    "delivery_address_full": "test",
    "customer_name": "123",
    "customer_phone_extra": null,
    "customer_phone": "99230125",
    "total_amount": 123,
    "delivery_count": 1,
    "delivery_driver_name": null,
    "tracking_number": "TSH-55RO6BDLAHXE",
    "delivery_status": "delivered",
    "payment_status": "pending",
    "created_at": "2025-06-09T10:16:10.376Z",
    "updated_at": null,
    "is_canceled": false,
    "canceled_reason": null
  },
  {
    "id": "8d90ddeb-4e18-47bd-854d-7f0b6b991a2c",
    "merchant_name": "Hishgee's shop",
    "delivery_address": {
      "address_details": "test",
      "address_notes": null
    },
    "pickup_address_full": null,
    "delivery_address_full": "test",
    "customer_name": "123",
    "customer_phone_extra": null,
    "customer_phone": "99230125",
    "total_amount": 123,
    "delivery_count": 1,
    "delivery_driver_name": null,
    "tracking_number": "HSH-IT9NDX2PHLRE",
    "delivery_status": "verified",
    "payment_status": "pending",
    "created_at": "2025-06-09T10:24:05.361Z",
    "updated_at": null,
    "is_canceled": false,
    "canceled_reason": null
  },
  {
    "id": "955d1cc1-d669-4d48-8a70-3db1ea770b95",
    "merchant_name": "Hishgee's shop",
    "delivery_address": null,
    "pickup_address_full": null,
    "delivery_address_full": "Баян зүрх дүүрэг 43 хороо 12 байр 32 тоот орцны код 3412_",
    "customer_name": "Тэмүжин",
    "customer_phone_extra": null,
    "customer_phone": "99230125",
    "total_amount": 100000,
    "delivery_count": 1,
    "delivery_driver_name": null,
    "tracking_number": "HSH-2U3T5PURJVWY",
    "delivery_status": "verified",
    "payment_status": "pending",
    "created_at": "2025-06-09T10:07:21.171Z",
    "updated_at": null,
    "is_canceled": false,
    "canceled_reason": null
  },
  {
    "id": "9ba1a49b-ecd6-4f3b-a6e4-1dc54dfc8312",
    "merchant_name": "Munkh-Orgil's Online Store",
    "delivery_address": {
      "address_details": "Nest Education dund surguuli, 5 davhar 501",
      "address_notes": null
    },
    "pickup_address_full": "Улаанбаатар, Сүхбаатар, 1-р хороо",
    "delivery_address_full": "Nest Education dund surguuli, 5 davhar 501",
    "customer_name": "Munkhorgil",
    "customer_phone_extra": null,
    "customer_phone": "86000660",
    "total_amount": 5000,
    "delivery_count": 1,
    "delivery_driver_name": null,
    "tracking_number": "MOS-3AC1KT1N2RZJ",
    "delivery_status": "verified",
    "payment_status": "pending",
    "created_at": "2025-06-12T04:41:24.207Z",
    "updated_at": null,
    "is_canceled": false,
    "canceled_reason": null
  },
  {
    "id": "c2444d90-3f80-496e-b886-8a18c20b8628",
    "merchant_name": "Temujin's shop",
    "delivery_address": null,
    "pickup_address_full": "Код байхгүй. Нохойтой учир болгоомжил",
    "delivery_address_full": "Баян зүрх дүүрэг 43 хороо 12 байр 32 тоот орцны код 3412_",
    "customer_name": "12123",
    "customer_phone_extra": null,
    "customer_phone": "99230125",
    "total_amount": 123,
    "delivery_count": 1,
    "delivery_driver_name": null,
    "tracking_number": "TSH-AF7BGNQUXTYA",
    "delivery_status": "created",
    "payment_status": "pending",
    "created_at": "2025-06-09T10:36:34.729Z",
    "updated_at": null,
    "is_canceled": false,
    "canceled_reason": null
  },
  {
    "id": "deecb4bf-dac0-48aa-bb5e-fa7c6f596663",
    "merchant_name": "Hishgee's shop",
    "delivery_address": {
      "address_details": "Баян зүрх дүүрэг 43 хороо 12 байр 32 тоот орцны код 3412_",
      "address_notes": null
    },
    "pickup_address_full": "ortsnii 4322#",
    "delivery_address_full": "Баян зүрх дүүрэг 43 хороо 12 байр 32 тоот орцны код 3412_",
    "customer_name": "test",
    "customer_phone_extra": null,
    "customer_phone": "99230125",
    "total_amount": 123,
    "delivery_count": 1,
    "delivery_driver_name": null,
    "tracking_number": "HSH-3P5KMXO6LQUD",
    "delivery_status": "created",
    "payment_status": "pending",
    "created_at": "2025-06-09T10:42:10.281Z",
    "updated_at": null,
    "is_canceled": false,
    "canceled_reason": null
  }
]
